{
  "$schema": "https://mintlify.com/docs.json",
  "name": "CertForge",
  "description": "Certificate governance platform — approval workflows, audit trails, and lifecycle management for TLS certificates.",
  "theme": "linden",
  "colors": {
    "primary": "#1d4ed8",
    "light": "#3b82f6",
    "dark": "#1e3a8a"
  },
  "favicon": "/favicon.ico",
  "logo": {
    "light": "/logo/light.svg",
    "dark": "/logo/dark.svg"
  },
  "icons": {
    "library": "lucide"
  },
  "navbar": {
    "links": [
      {
        "label": "Sign In",
        "href": "https://app.certforge.xyz/login"
      }
    ],
    "primary": {
      "type": "button",
      "label": "Get Started",
      "href": "https://app.certforge.xyz"
    }
  },
  "navigation": {
    "global": {
      "anchors": [
        {
          "anchor": "certforge.xyz",
          "icon": "house",
          "href": "https://certforge.xyz"
        },
        {
          "anchor": "Changelog",
          "icon": "scroll-text",
          "href": "https://certforge.xyz/changelog"
        },
        {
          "anchor": "Support",
          "icon": "life-buoy",
          "href": "mailto:support@certforge.xyz"
        }
      ]
    },
    "groups": [
      {
        "group": "Getting Started",
        "icon": "rocket",
        "pages": [
          "introduction",
          "self-hosted/requirements",
          "self-hosted/quick-start"
        ]
      },
      {
        "group": "Self-Hosted Installation",
        "icon": "server",
        "pages": [
          "self-hosted/installation",
          "self-hosted/systemd",
          "self-hosted/configuration",
          "self-hosted/upgrading"
        ]
      },
      {
        "group": "Core Concepts",
        "icon": "book-open",
        "pages": [
          "concepts/domain-trust-profiles",
          "concepts/certificate-lifecycle",
          "concepts/approvals",
          "concepts/alerts",
          "concepts/devices",
          "concepts/licensing"
        ]
      },
      {
        "group": "Guides",
        "icon": "map",
        "pages": [
          "guides/acme-setup",
          "guides/internal-ca",
          "guides/dns-validation",
          "guides/approval-workflow",
          "guides/email-setup"
        ]
      },
      {
        "group": "Reference",
        "icon": "code",
        "pages": [
          "reference/configuration",
          "reference/api",
          "reference/license-jwt"
        ]
      }
    ]
  },
  "footer": {
    "socials": {
      "website": "https://certforge.xyz"
    }
  }
}
